Workbook
Name aporte: APP!$D$17
Name patrimonio: APP!$D$20
Name qtde_anos: APP!$D$18
Name rendimento_carteira: APP!$D$13
Name salario: APP!$B$12
Name sugestao: APP!$B$14
Name taxa_anos: APP!$D$19

Sheet APP
B11: CONFIGURAÇÕES
B12: Salário | D12: 5000
B13: Rendimento carteira | D13: 0.006
B14: Sugestão de investimento | D14: =D12*30% -> 1500
B16: INVESTIMENTO MENSAL
B17: Quanto investir por mês? | D17: 500
B18: Por quantos anos? | D18: 5
B19: Taxa de rendimento mensal? | D19: 0.01079
B20: Patrimônio acumulado? | D20: =FV(taxa_anos,qtde_anos*12,aporte*-1) -> 41888.457
B21: Dividendos mensais? | D21: =patrimonio*$D$13 -> 251.33074
B23: CENÁRIOS | D23: Dividendos
A24: 2 | B24: Quanto em 02 anos? | C24: =FV($D$19,$A24*12,$D$17*-1) -> 13613.814 | D24: =C24*rendimento_carteira -> 81.682882
A25: 5 | B25: Quanto em 05 anos? | C25: =FV($D$19,$A25*12,$D$17*-1) -> 41888.457 | D25: =C25*rendimento_carteira -> 251.33074
A26: 10 | B26: Quanto em 10 anos? | C26: =FV($D$19,$A26*12,$D$17*-1) -> 121642.11 | D26: =C26*rendimento_carteira -> 729.85264
A27: 20 | B27: Quanto em 20 anos? | C27: =FV($D$19,$A27*12,$D$17*-1) -> 562599.2 | D27: =C27*rendimento_carteira -> 3375.5952
A28: 30 | B28: Quanto em 30 anos? | C28: =FV($D$19,$A28*12,$D$17*-1) -> 2161084.8 | D28: =C28*rendimento_carteira -> 12966.509
B30: PERFIL | C30: AGRESSIVO
B31: VALOR A SER INVESTIDO POR MÊS | C31: 250
B33: TIPOS DE FI | C33: Percentual sugerido | D33: Valores
B34: PAPEL | C34: =VLOOKUP($C$30&"-"&B34,PlanilhadeApoio!A:D,4,FALSE) -> 0.5 | D34: =C34*$C$31 -> 125
B35: TIJOLO | C35: =VLOOKUP($C$30&"-"&B35,PlanilhadeApoio!A:D,4,FALSE) -> 0.1 | D35: =C35*$C$31 -> 25
B36: HÍBRIDOS | C36: =VLOOKUP($C$30&"-"&B36,PlanilhadeApoio!A:D,4,FALSE) -> 0.05 | D36: =C36*$C$31 -> 12.5
B37: FOF´s | C37: =VLOOKUP($C$30&"-"&B37,PlanilhadeApoio!A:D,4,FALSE) -> 0.05 | D37: =C37*$C$31 -> 12.5
B38: DESENVOLVIMENTO | C38: =VLOOKUP($C$30&"-"&B38,PlanilhadeApoio!A:D,4,FALSE) -> 0.2 | D38: =C38*$C$31 -> 50
B39: HOTELARIA | C39: =VLOOKUP($C$30&"-"&B39,PlanilhadeApoio!A:D,4,FALSE) -> 0.1 | D39: =C39*$C$31 -> 25
D40: =SUM(D34:D39) -> 250

Sheet PlanilhadeApoio
A4: CHAVE | B4: PERFIL | C4: TIPOS DE FI | D4: %
A5: =B5&"-"&C5 -> CONSERVADOR-PAPEL | B5: CONSERVADOR | C5: PAPEL | D5: 0.3
A6: =B6&"-"&C6 -> CONSERVADOR-TIJOLO | B6: CONSERVADOR | C6: TIJOLO | D6: 0.5 | G6: MODERADO-TIJOLO | H6: =VLOOKUP(G6,$A:$D,4,) -> 0.4
A7: =B7&"-"&C7 -> CONSERVADOR-HÍBRIDOS | B7: CONSERVADOR | C7: HÍBRIDOS | D7: 0.1
A8: =B8&"-"&C8 -> CONSERVADOR-FOF´s | B8: CONSERVADOR | C8: FOF´s | D8: 0.1
A9: =B9&"-"&C9 -> CONSERVADOR-DESENVOLVIMENTO | B9: CONSERVADOR | C9: DESENVOLVIMENTO | D9: 0
A10: =B10&"-"&C10 -> CONSERVADOR-HOTELARIA | B10: CONSERVADOR | C10: HOTELARIA | D10: 0
A11: =B11&"-"&C11 -> MODERADO-PAPEL | B11: MODERADO | C11: PAPEL | D11: 0.22
A12: =B12&"-"&C12 -> MODERADO-TIJOLO | B12: MODERADO | C12: TIJOLO | D12: 0.4
A13: =B13&"-"&C13 -> MODERADO-HÍBRIDOS | B13: MODERADO | C13: HÍBRIDOS | D13: 0.08
A14: =B14&"-"&C14 -> MODERADO-FOF´s | B14: MODERADO | C14: FOF´s | D14: 0.1
A15: =B15&"-"&C15 -> MODERADO-DESENVOLVIMENTO | B15: MODERADO | C15: DESENVOLVIMENTO | D15: 0.1
A16: =B16&"-"&C16 -> MODERADO-HOTELARIA | B16: MODERADO | C16: HOTELARIA | D16: 0.1
A17: =B17&"-"&C17 -> AGRESSIVO-PAPEL | B17: AGRESSIVO | C17: PAPEL | D17: 0.5
A18: =B18&"-"&C18 -> AGRESSIVO-TIJOLO | B18: AGRESSIVO | C18: TIJOLO | D18: 0.1
... A22: =B22&"-"&C22 -> AGRESSIVO-HOTELARIA | B22: AGRESSIVO | C22: HOTELARIA | D22: 0.1
